bpm/__init__.py
bpm/__main__.py
bpm/cli.py
bpm/command.py
bpm/storage.py
bpm/install/__init__.py
bpm/lib/windowspathadder.py
bpm/search/__init__.py
bpm/search/arch_select.py
bpm/utils/__init__.py
bpm/utils/constants.py
bpm/utils/exceptions.py
bpm/utils/input.py
bin_package_manager-2.3.0.dist-info/METADATA
bin_package_manager-2.3.0.dist-info/WHEEL
bin_package_manager-2.3.0.dist-info/entry_points.txt
bin_package_manager-2.3.0.dist-info/licenses/LICENSE
bin_package_manager-2.3.0.dist-info/RECORD
