Metadata-Version: 2.4
Name: bin-package-manager
Version: 2.3.0
Summary: Bin package manager, a package manager based on Github release
Project-URL: Repository, https://github.com/lxl66566/bpm
Project-URL: Homepage, https://github.com/lxl66566/bpm
Author-email: lxl66566 <lxl66566@gmail.com>
License-Expression: MIT
License-File: LICENSE
Keywords: binary,packaging,release
Classifier: License :: OSI Approved :: MIT License
Classifier: Operating System :: OS Independent
Classifier: Programming Language :: Python :: 3
Classifier: Programming Language :: Python :: 3.9
Classifier: Programming Language :: Python :: 3.10
Classifier: Programming Language :: Python :: 3.11
Classifier: Programming Language :: Python :: 3.12
Requires-Python: >=3.9
Requires-Dist: pretty-assert>=0.1.1
Requires-Dist: pylnk3>=0.4.2
Requires-Dist: questionary>=2.1.0
Requires-Dist: requests>=2.32.3
Requires-Dist: tqdm>=4.66.5
